odoo10_addon_save_translation_file-10.0.1.0.0.99.dev2-py3.8-nspkg.pth
odoo/addons/save_translation_file/README.rst
odoo/addons/save_translation_file/__init__.py
odoo/addons/save_translation_file/__manifest__.py
odoo/addons/save_translation_file/i18n/de.po
odoo/addons/save_translation_file/i18n/es.po
odoo/addons/save_translation_file/i18n/fr.po
odoo/addons/save_translation_file/i18n/it.po
odoo/addons/save_translation_file/i18n/save_translation_file.pot
odoo/addons/save_translation_file/i18n/sl.po
odoo/addons/save_translation_file/i18n/tr.po
odoo/addons/save_translation_file/models/__init__.py
odoo/addons/save_translation_file/models/save_translation_file.py
odoo/addons/save_translation_file/static/description/icon.png
odoo/addons/save_translation_file/tests/__init__.py
odoo/addons/save_translation_file/tests/test_save_translation_file.py
odoo/addons/save_translation_file/views/save_translation_file_view.xml
odoo10_addon_save_translation_file-10.0.1.0.0.99.dev2.dist-info/METADATA
odoo10_addon_save_translation_file-10.0.1.0.0.99.dev2.dist-info/WHEEL
odoo10_addon_save_translation_file-10.0.1.0.0.99.dev2.dist-info/namespace_packages.txt
odoo10_addon_save_translation_file-10.0.1.0.0.99.dev2.dist-info/top_level.txt
odoo10_addon_save_translation_file-10.0.1.0.0.99.dev2.dist-info/RECORD
